phone_management_plugin/__init__.py
phone_management_plugin/choices.py
phone_management_plugin/filtersets.py
phone_management_plugin/forms.py
phone_management_plugin/models.py
phone_management_plugin/navigation.py
phone_management_plugin/signals.py
phone_management_plugin/tables.py
phone_management_plugin/template_content.py
phone_management_plugin/urls.py
phone_management_plugin/views.py
phone_management_plugin/api/serializers.py
phone_management_plugin/api/urls.py
phone_management_plugin/api/views.py
phone_management_plugin/migrations/0001_initial.py
phone_management_plugin/migrations/0002_rename_voice_cicruit_phonenumber_voice_circuit_and_more.py
phone_management_plugin/migrations/0003_sim_device.py
phone_management_plugin/migrations/0004_alter_phonenumber_options_and_more.py
phone_management_plugin/migrations/0005_rename_incoming_dailpeer_phonenumber_incoming_dialpeer_and_more.py
phone_management_plugin/migrations/0006_rename_virtual_circuit_phonenumber_primary_virtual_circuit_and_more.py
phone_management_plugin/migrations/__init__.py
phone_management_plugin/templates/phone_management_plugin/phonenumber.html
phone_management_plugin/templates/phone_management_plugin/phonenumberrange.html
phone_management_plugin/templates/phone_management_plugin/sim.html
phone_management_plugin/templates/phone_management_plugin/simadmin.html
phone_management_plugin/templates/phone_management_plugin/inc/device_info.html
phone_management_plugin-0.2.2.dist-info/METADATA
phone_management_plugin-0.2.2.dist-info/WHEEL
phone_management_plugin-0.2.2.dist-info/top_level.txt
phone_management_plugin-0.2.2.dist-info/RECORD
