Metadata-Version: 2.4
Name: phone_management_plugin
Version: 0.2.2
Summary: Netbox phone_management_plugin plugin
Author-email: Mattijs Vanhaverbeke <author@example.com>
Classifier: Intended Audience :: Developers
Classifier: Natural Language :: English
Classifier: Programming Language :: Python :: 3 :: Only
Classifier: Programming Language :: Python :: 3.10
Classifier: Programming Language :: Python :: 3.11
Classifier: Programming Language :: Python :: 3.12
Requires-Python: >=3.10.0
